[
    {
        "title": "Fractura", 
        "data": [
            {
                "name":"Vertical",
                "id":"vertical",
                "type": "fractura"
            },
            {
                "name":"Horizontal",
                "id":"horizontal",
                "type": "fractura"
            }
        ]
    },
    {
        "name":"Caries",
        "id":"caries",
        "type": "eva"
    },
    {
        "name":"Trauma",
        "id":"trauma",
        "type": "eva"
    },
    {
        "name":"Absceso",
        "id":"absceso",
        "type": "eva"
    },
    {
        "name":"Discromia",
        "id":"discromia",
        "type": "eva"
    },
    {
        "name":"Fistula",
        "id":"fistula",
        "type": "eva"
    },
    {
        "name":"Interna",
        "id":"interna",
        "type": "reabsorcion"
    },
    {
        "name":"Externa",
        "id":"externa",
        "type": "reabsorcion"
    },
    {
        "name":"Endodoncia por razon prostetica",
        "id":"endodonciaProstetica",
        "type": "eva"
    },
    {
        "name":"1",
        "id":"movilidad1",
        "type": "movilidad"
    },
    {
        "name":"2",
        "id":"movilidad2",
        "type": "movilidad"
    },
    {
        "name":"3",
        "id":"movilidad3",
        "type": "movilidad"
    },
    {
        "name":"Sobreobturado",
        "id":"sobreobturado",
        "type": "reendodoncia"
    },
    {
        "name":"Subobturado",
        "id":"subobturado",
        "type": "reendodoncia"
    },
    {
        "name":"Incompleto",
        "id":"incompleto",
        "type": "reendodoncia"
    },
    {
        "name":"Reinfeccion",
        "id":"reinfeccion",
        "type": "reendodoncia"
    },
    {
        "name":"Espontaneo",
        "id":"espontaneo",
        "type": "dolorTipo"
    },
    {
        "name":"Continuo",
        "id":"continuo",
        "type": "dolorTipo"
    },
    {
        "name":"Palpitante",
        "id":"palpitante",
        "type": "dolorTipo"
    },
    {
        "name":"Calor",
        "id":"calor",
        "type": "dolorEstimulado"
    },
    {
        "name":"Frio",
        "id":"frio",
        "type": "dolorEstimulado"
    },
    {
        "name":"Masticacion",
        "id":"masticacion",
        "type": "dolorEstimulado"
    },
    {
        "name":"Acidos",
        "id":"acidos",
        "type": "dolorEstimulado"
    },
    {
        "name":"Dulces",
        "id":"dulces",
        "type": "dolorEstimulado"
    },
    {
        "name":"Leve",
        "id":"Leve",
        "type": "dolorIntencidad"
    },
    {
        "name":"Moderada",
        "id":"moderada",
        "type": "dolorIntencidad"
    },
    {
        "name":"Severa",
        "id":"severa",
        "type": "dolorIntencidad"
    },
    {
        "name":"Periapical inicial",
        "id":"periapicalInicial",
        "type": "estudios"
    },
    {
        "name":"Periapical final",
        "id":"periapicalFinal",
        "type": "estudios"
    },
    {
        "name":"OPG",
        "id":"opg",
        "type": "estudios"
    },
    {
        "name":"TAC",
        "id":"tac",
        "type": "estudios"
    },
    {
        "name": "Frio",
        "id": "frio+",
        "id1": "frio-",
        "type": "pruebasVitalidad"
    },
    {
        "name": "Calor",
        "id": "calor+",
        "id1": "calor-",
        "type": "pruebasVitalidad"
    },
    {
        "name": "Palpitacion",
        "id": "palpitacion+",
        "id1": "palpitacion-",
        "type": "pruebasVitalidad"
    },
    {
        "name": "Presion",
        "id": "presion+",
        "id1": "presion-",
        "type": "pruebasVitalidad"
    }
]